Workbook

Sheet Hoja1
B1: GRADO QUIRÚRGICO S.A DE C.V RFC: GQU210304NJ5, Calle Central de Abastos Nave F, Local 21, San Vicente Chicoloapan de Juárez Centro, Chicoloapan, CP. 56370, EDOMEX. | E1: FECHA DE PEDIDO: | G1: CONDICIONES DE PAGO: | I1: SUCURSAL DESTINO:
A2: PROVEEDOR: | E2: CANTIDAD DE PRODUCTOS: | G2: No. DE ORDEN DE COMPRA: | I2: NO. COTIZACIÓN:
J3: REPARTO
A4: CÓDIGO | B4: DESCRIPCIÓN | C4: PIEZAS | D4: UNITARIO BRUTO | E4: PRECIO | F4: TOTAL | G4: IMPUESTOS | H4: TOTAL BRUTO | I4: IMPUESTOS | J4: F37 | K4: F35 | L4: GH | M4: SV | N4: ECA | S4: 28 COSMETICS | T4: Pago inmediato | U4: Ecatepec
D5: =E5/G5 -> 0 | F5: =C5*E5 -> 0 | G5: =IF(_xlfn.XLOOKUP(A5,MACHOTE!A:A,MACHOTE!V:V,0,0)="S",1.16,IF(_xlfn.XLOOKUP(A5,MACHOTE!A:A,MACHOTE!Y:Y,0,0)="S",1.08,1)) -> 1 | H5: =D5*C5 -> 0 | I5: =F5-H5 -> 0 | S5: ALEJANDRO MARTINEZ PONCE | T5: 15 días | U5: Iztapalapa F35
S6: Alejandro Villagomez Castro | T6: 21 días | U6: Iztapalapa F37
S7: BRONCOLIN | T7: 30 días | U7: Iztapalapa GH
S8: BRUDIFARMA | T8: 45 días | U8: San Vicente
S9: CARLOS ANTONIO ZUÑIGA ORTEGA | T9: Fin del siguiente mes | U9: CEDIS IZTAPALAPA GH
S10: CETUS FARMACEUTICA | T10: 10 días después del fin del siguiente mes | U10: CEDIS San Vicente
S11: COMERCIAL G.F.C. | T11: 30% ahora, el resto en 60 días
S12: COMERCIALIZADORA COYOQUIMEX DEL BAJIO | T12: 2/7 neto 30
S13: COMERCIALIZADORA DIBAR | T13: 90 días, en el día 10
S14: CORPORACION NACIONAL DE ABASTO FARMACEUTICOS | T14: 13 días
S15: Cristobal Mendoza Lopez | T15: 7 días
S16: DENTILAB | T16: 60 días
S17: DIANA ALEJANDRA GUZMAN MIRANDA
S18: DIFARMER
S19: DISAGS FARMACEUTICA
S20: DISTRIBUCION FARMACEUTICA YALESA
S21: DISTRIBUCIONES MDMX GDL
S22: DISTRIBUIDORA BIOLIFE
S23: DISTRIBUIDORA FARMACEUTICA CALDERON
S24: Dylan Villagomez Johnson
S25: EMANUEL ATAI REYES LEWIS
S26: Ecatepec
S27: FARMA CRÜE
S28: FARMA GENEX
... S69: sandrareyesramirez@gmail.com

Sheet OC
B1: GRADO QUIRÚRGICO S.A DE C.V RFC: GQU210304NJ5, Calle Central de Abastos Nave F, Local 21, San Vicente Chicoloapan de Juárez Centro, Chicoloapan, CP. 56370, EDOMEX.
A2: PROVEEDOR:
A3: FECHA DE PEDIDO:
A4: CONDICIONES DE PAGO:
A5: No. DE ORDEN DE COMPRA:
A6: SUCURSAL DESTINO: | S6: ALEJANDRO VILLAGOMEZ
A7: CLASE DE MOVIMIENTO | S7: MIGUEL ANGEL REYES MENDIETA
A8: FOLIO COTIZACIÓN | J8: REPARTO | S8: RICARDO HEREDIA
A9: CÓDIGO | B9: DESCRIPCIÓN | C9: PIEZAS | D9: UNITARIO BRUTO | E9: PRECIO MXN | F9: TOTAL | G9: IMPUESTOS | H9: TOTAL BRUTO | I9: IMPUESTOS | J9: F37 | K9: F35 | L9: GH | M9: SV | N9: ECA | P9: FACTOR | S9: 28 COSMETICS | T9: Pago inmediato | U9: Ecatepec
D10: =E10/G10 -> 0 | F10: =C10*E10 -> 0 | G10: =IF(_xlfn.XLOOKUP(A10,MACHOTE!A:A,MACHOTE!V:V,0,0)="S",1.16,IF(_xlfn.XLOOKUP(A10,MACHOTE!A:A,MACHOTE!Y:Y,0,0)="S",1.08,1)) -> 1 | H10: =D10*C10 -> 0 | I10: =F10-H10 -> 0 | S10: ALEJANDRO MARTINEZ PONCE | T10: 15 días | U10: Iztapalapa F35
D11: =E11/G11 -> 0 | F11: =C11*E11 -> 0 | G11: =IF(_xlfn.XLOOKUP(A11,MACHOTE!A:A,MACHOTE!V:V,0,0)="S",1.16,IF(_xlfn.XLOOKUP(A11,MACHOTE!A:A,MACHOTE!Y:Y,0,0)="S",1.08,1)) -> 1 | H11: =D11*C11 -> 0 | I11: =F11-H11 -> 0 | S11: SANFER | T11: 21 días | U11: Iztapalapa F37
S12: BRONCOLIN | T12: 30 días | U12: Iztapalapa GH
S13: BRUDIFARMA | T13: 45 días | U13: San Vicente
S14: CARLOS ANTONIO ZUÑIGA ORTEGA | T14: Fin del siguiente mes | U14: CEDIS IZTAPALAPA GH
S15: CETUS FARMACEUTICA | T15: 10 días después del fin del siguiente mes | U15: CEDIS San Vicente
S16: COMERCIAL G.F.C. | T16: 30% ahora, el resto en 60 días
S17: COMERCIALIZADORA COYOQUIMEX DEL BAJIO | T17: 2/7 neto 30
S18: COMERCIALIZADORA DIBAR | T18: 90 días, en el día 10
S19: CORPORACION NACIONAL DE ABASTO FARMACEUTICOS | T19: 13 días
S20: Cristobal Mendoza Lopez | T20: 7 días
S21: DENTILAB DL | T21: 60 días
S22: DIANA ALEJANDRA GUZMAN MIRANDA
S23: DIFARMER
S24: DISAGS FARMACEUTICA
S25: DISTRIBUCION FARMACEUTICA YALESA
S26: DISTRIBUCIONES MDMX GDL
S27: DISTRIBUIDORA BIOLIFE
S28: DISTRIBUIDORA FARMACEUTICA CALDERON
S29: Dylan Villagomez Johnson
S30: EMANUEL ATAI REYES LEWIS
S31: Ecatepec
S32: FARMA CRÜE
S33: FARMA GENEX
... S77: REBOTICA MADRID

Sheet lay out
A1: CODIGO | B1: DESCRIPCIÓN | C1: PIEZAS | D1: MULTIPLO DE COMPRA | E1: UNITARIO BRUTO | F1: PRECIO | G1: TOTAL | H1: IMPUESTOS | I1: TOTAL BRUTO | J1: IMPUESTOS | K1: SUCURSAL DESTINO | L1: CLASE DE MOVIMIENTO | M1: PROVEEDOR | N1: FECHA DE PEDIDO | O1: No. DE ORDEN DE COMPRA | P1: FOLIO COTIZACIÓN | Q1: CONDICION DE PAGO | R1: F37 | S1: F35 | T1: GH | U1: SV | V1: ECA
A2: =OC!A10 -> 0 | B2: =OC!B10 -> 0 | C2: =OC!C10 -> 0 | D2: =OC!P10 -> 0 | E2: =OC!D10 -> 0 | F2: =OC!E10 -> 0 | G2: =C2*F2 -> 0 | H2: =IF(_xlfn.XLOOKUP(A2,[1]MACHOTE!A:A,[1]MACHOTE!V:V,0,0)="S",1.16,IF(_xlfn.XLOOKUP(A2,[1]MACHOTE!A:A,[1]MACHOTE!Y:Y,0,0)="S",1.08,1)) -> 1 | I2: =E2*C2 -> 0 | J2: =G2-I2 -> 0 | K2: =OC!$B$6 -> 0 | L2: =OC!$B$7 -> 0 | M2: =OC!$B$2 -> 0 | N2: =OC!$B$3 -> 0 | O2: =OC!$B$5 -> 0 | P2: =OC!$B$8 -> 0 | Q2: =OC!$B$4 -> 0 | R2: =OC!J10 -> 0 | S2: 0 | T2: =OC!L10 -> 0 | U2: =OC!M10 -> 0 | V2: =OC!N10 -> 0
A3: =OC!A11 -> 0 | B3: =OC!B11 -> 0 | C3: =OC!C11 -> 0 | D3: =OC!P11 -> 0 | E3: =OC!D11 -> 0 | F3: =OC!E11 -> 0 | G3: =C3*F3 -> 0 | H3: =IF(_xlfn.XLOOKUP(A3,[1]MACHOTE!A:A,[1]MACHOTE!V:V,0,0)="S",1.16,IF(_xlfn.XLOOKUP(A3,[1]MACHOTE!A:A,[1]MACHOTE!Y:Y,0,0)="S",1.08,1)) -> 1 | I3: =E3*C3 -> 0 | J3: =G3-I3 -> 0 | K3: =OC!$B$6 -> 0 | L3: =OC!$B$7 -> 0 | M3: =OC!$B$2 -> 0 | N3: =OC!$B$3 -> 0 | O3: =OC!$B$5 -> 0 | P3: =OC!$B$8 -> 0 | Q3: =OC!$B$4 -> 0 | R3: =OC!J11 -> 0 | S3: 0 | T3: =OC!M11 -> 0 | U3: =OC!N11 -> 0 | V3: =OC!N11 -> 0
A4: =OC!A12 -> 0 | B4: =OC!B12 -> 0 | C4: =OC!C12 -> 0 | D4: =OC!P12 -> 0 | E4: =OC!D12 -> 0 | F4: =OC!E12 -> 0 | G4: =C4*F4 -> 0 | H4: =IF(_xlfn.XLOOKUP(A4,[1]MACHOTE!A:A,[1]MACHOTE!V:V,0,0)="S",1.16,IF(_xlfn.XLOOKUP(A4,[1]MACHOTE!A:A,[1]MACHOTE!Y:Y,0,0)="S",1.08,1)) -> 1 | I4: =E4*C4 -> 0 | J4: =G4-I4 -> 0 | K4: =OC!$B$6 -> 0 | L4: =OC!$B$7 -> 0 | M4: =OC!$B$2 -> 0 | N4: =OC!$B$3 -> 0 | O4: =OC!$B$5 -> 0 | P4: =OC!$B$8 -> 0 | Q4: =OC!$B$4 -> 0 | R4: =OC!J12 -> 0 | S4: 0 | T4: =OC!M12 -> 0 | U4: =OC!N12 -> 0 | V4: =OC!N12 -> 0
A5: =OC!A13 -> 0 | B5: =OC!B13 -> 0 | C5: =OC!C13 -> 0 | D5: =OC!P13 -> 0 | E5: =OC!D13 -> 0 | F5: =OC!E13 -> 0 | G5: =C5*F5 -> 0 | H5: =IF(_xlfn.XLOOKUP(A5,[1]MACHOTE!A:A,[1]MACHOTE!V:V,0,0)="S",1.16,IF(_xlfn.XLOOKUP(A5,[1]MACHOTE!A:A,[1]MACHOTE!Y:Y,0,0)="S",1.08,1)) -> 1 | I5: =E5*C5 -> 0 | J5: =G5-I5 -> 0 | K5: =OC!$B$6 -> 0 | L5: =OC!$B$7 -> 0 | M5: =OC!$B$2 -> 0 | N5: =OC!$B$3 -> 0 | O5: =OC!$B$5 -> 0 | P5: =OC!$B$8 -> 0 | Q5: =OC!$B$4 -> 0 | R5: =OC!J13 -> 0 | S5: 0 | T5: =OC!L13 -> 0 | U5: =OC!M13 -> 0 | V5: =OC!N13 -> 0
A6: =OC!A14 -> 0 | B6: =OC!B14 -> 0 | C6: =OC!C14 -> 0 | D6: =OC!P14 -> 0 | E6: =OC!D14 -> 0 | F6: =OC!E14 -> 0 | G6: =C6*F6 -> 0 | H6: =IF(_xlfn.XLOOKUP(A6,[1]MACHOTE!A:A,[1]MACHOTE!V:V,0,0)="S",1.16,IF(_xlfn.XLOOKUP(A6,[1]MACHOTE!A:A,[1]MACHOTE!Y:Y,0,0)="S",1.08,1)) -> 1 | I6: =E6*C6 -> 0 | J6: =G6-I6 -> 0 | K6: =OC!$B$6 -> 0 | L6: =OC!$B$7 -> 0 | M6: =OC!$B$2 -> 0 | N6: =OC!$B$3 -> 0 | O6: =OC!$B$5 -> 0 | P6: =OC!$B$8 -> 0 | Q6: =OC!$B$4 -> 0 | R6: =OC!J14 -> 0 | S6: 0 | T6: =OC!L14 -> 0 | U6: =OC!M14 -> 0 | V6: =OC!N14 -> 0
A7: =OC!A15 -> 0 | B7: =OC!B15 -> 0 | C7: =OC!C15 -> 0 | D7: =OC!P15 -> 0 | E7: =OC!D15 -> 0 | F7: =OC!E15 -> 0 | G7: =C7*F7 -> 0 | H7: =IF(_xlfn.XLOOKUP(A7,[1]MACHOTE!A:A,[1]MACHOTE!V:V,0,0)="S",1.16,IF(_xlfn.XLOOKUP(A7,[1]MACHOTE!A:A,[1]MACHOTE!Y:Y,0,0)="S",1.08,1)) -> 1 | I7: =E7*C7 -> 0 | J7: =G7-I7 -> 0 | K7: =OC!$B$6 -> 0 | L7: =OC!$B$7 -> 0 | M7: =OC!$B$2 -> 0 | N7: =OC!$B$3 -> 0 | O7: =OC!$B$5 -> 0 | P7: =OC!$B$8 -> 0 | Q7: =OC!$B$4 -> 0 | R7: =OC!J15 -> 0 | S7: 0 | T7: =OC!L15 -> 0 | U7: =OC!M15 -> 0 | V7: =OC!N15 -> 0
A8: =OC!A16 -> 0 | B8: =OC!B16 -> 0 | C8: =OC!C16 -> 0 | D8: =OC!P16 -> 0 | E8: =OC!D16 -> 0 | F8: =OC!E16 -> 0 | G8: =C8*F8 -> 0 | H8: =IF(_xlfn.XLOOKUP(A8,[1]MACHOTE!A:A,[1]MACHOTE!V:V,0,0)="S",1.16,IF(_xlfn.XLOOKUP(A8,[1]MACHOTE!A:A,[1]MACHOTE!Y:Y,0,0)="S",1.08,1)) -> 1 | I8: =E8*C8 -> 0 | J8: =G8-I8 -> 0 | K8: =OC!$B$6 -> 0 | L8: =OC!$B$7 -> 0 | M8: =OC!$B$2 -> 0 | N8: =OC!$B$3 -> 0 | O8: =OC!$B$5 -> 0 | P8: =OC!$B$8 -> 0 | Q8: =OC!$B$4 -> 0 | R8: =OC!J16 -> 0 | S8: 0 | T8: =OC!L16 -> 0 | U8: =OC!M16 -> 0 | V8: =OC!N16 -> 0
A9: =OC!A17 -> 0 | B9: =OC!B17 -> 0 | C9: =OC!C17 -> 0 | D9: =OC!P17 -> 0 | E9: =OC!D17 -> 0 | F9: =OC!E17 -> 0 | G9: =C9*F9 -> 0 | H9: =IF(_xlfn.XLOOKUP(A9,[1]MACHOTE!A:A,[1]MACHOTE!V:V,0,0)="S",1.16,IF(_xlfn.XLOOKUP(A9,[1]MACHOTE!A:A,[1]MACHOTE!Y:Y,0,0)="S",1.08,1)) -> 1 | I9: =E9*C9 -> 0 | J9: =G9-I9 -> 0 | K9: =OC!$B$6 -> 0 | L9: =OC!$B$7 -> 0 | M9: =OC!$B$2 -> 0 | N9: =OC!$B$3 -> 0 | O9: =OC!$B$5 -> 0 | P9: =OC!$B$8 -> 0 | Q9: =OC!$B$4 -> 0 | R9: =OC!J17 -> 0 | S9: 0 | T9: =OC!L17 -> 0 | U9: =OC!M17 -> 0 | V9: =OC!N17 -> 0
A10: =OC!A18 -> 0 | B10: =OC!B18 -> 0 | C10: =OC!C18 -> 0 | D10: =OC!P18 -> 0 | E10: =OC!D18 -> 0 | F10: =OC!E18 -> 0 | G10: =C10*F10 -> 0 | H10: =IF(_xlfn.XLOOKUP(A10,[1]MACHOTE!A:A,[1]MACHOTE!V:V,0,0)="S",1.16,IF(_xlfn.XLOOKUP(A10,[1]MACHOTE!A:A,[1]MACHOTE!Y:Y,0,0)="S",1.08,1)) -> 1 | I10: =E10*C10 -> 0 | J10: =G10-I10 -> 0 | K10: =OC!$B$6 -> 0 | L10: =OC!$B$7 -> 0 | M10: =OC!$B$2 -> 0 | N10: =OC!$B$3 -> 0 | O10: =OC!$B$5 -> 0 | P10: =OC!$B$8 -> 0 | Q10: =OC!$B$4 -> 0 | R10: =OC!J18 -> 0 | S10: 0 | T10: =OC!L18 -> 0 | U10: =OC!M18 -> 0 | V10: =OC!N18 -> 0
A11: =OC!A19 -> 0 | B11: =OC!B19 -> 0 | C11: =OC!C19 -> 0 | D11: =OC!P19 -> 0 | E11: =OC!D19 -> 0 | F11: =OC!E19 -> 0 | G11: =C11*F11 -> 0 | H11: =IF(_xlfn.XLOOKUP(A11,[1]MACHOTE!A:A,[1]MACHOTE!V:V,0,0)="S",1.16,IF(_xlfn.XLOOKUP(A11,[1]MACHOTE!A:A,[1]MACHOTE!Y:Y,0,0)="S",1.08,1)) -> 1 | I11: =E11*C11 -> 0 | J11: =G11-I11 -> 0 | K11: =OC!$B$6 -> 0 | L11: =OC!$B$7 -> 0 | M11: =OC!$B$2 -> 0 | N11: =OC!$B$3 -> 0 | O11: =OC!$B$5 -> 0 | P11: =OC!$B$8 -> 0 | Q11: =OC!$B$4 -> 0 | R11: =OC!J19 -> 0 | S11: 0 | T11: =OC!L19 -> 0 | U11: =OC!M19 -> 0 | V11: =OC!N19 -> 0
A12: =OC!A20 -> 0 | B12: =OC!B20 -> 0 | C12: =OC!C20 -> 0 | D12: =OC!P20 -> 0 | E12: =OC!D20 -> 0 | F12: =OC!E20 -> 0 | G12: =C12*F12 -> 0 | H12: =IF(_xlfn.XLOOKUP(A12,[1]MACHOTE!A:A,[1]MACHOTE!V:V,0,0)="S",1.16,IF(_xlfn.XLOOKUP(A12,[1]MACHOTE!A:A,[1]MACHOTE!Y:Y,0,0)="S",1.08,1)) -> 1 | I12: =E12*C12 -> 0 | J12: =G12-I12 -> 0 | K12: =OC!$B$6 -> 0 | L12: =OC!$B$7 -> 0 | M12: =OC!$B$2 -> 0 | N12: =OC!$B$3 -> 0 | O12: =OC!$B$5 -> 0 | P12: =OC!$B$8 -> 0 | Q12: =OC!$B$4 -> 0 | R12: =OC!J20 -> 0 | S12: 0 | T12: =OC!L20 -> 0 | U12: =OC!M20 -> 0 | V12: =OC!N20 -> 0
A13: =OC!A21 -> 0 | B13: =OC!B21 -> 0 | C13: =OC!C21 -> 0 | D13: =OC!P21 -> 0 | E13: =OC!D21 -> 0 | F13: =OC!E21 -> 0 | G13: =C13*F13 -> 0 | H13: =IF(_xlfn.XLOOKUP(A13,[1]MACHOTE!A:A,[1]MACHOTE!V:V,0,0)="S",1.16,IF(_xlfn.XLOOKUP(A13,[1]MACHOTE!A:A,[1]MACHOTE!Y:Y,0,0)="S",1.08,1)) -> 1 | I13: =E13*C13 -> 0 | J13: =G13-I13 -> 0 | K13: =OC!$B$6 -> 0 | L13: =OC!$B$7 -> 0 | M13: =OC!$B$2 -> 0 | N13: =OC!$B$3 -> 0 | O13: =OC!$B$5 -> 0 | P13: =OC!$B$8 -> 0 | Q13: =OC!$B$4 -> 0 | R13: =OC!J21 -> 0 | S13: 0 | T13: =OC!L21 -> 0 | U13: =OC!M21 -> 0 | V13: =OC!N21 -> 0
A14: =OC!A22 -> 0 | B14: =OC!B22 -> 0 | C14: =OC!C22 -> 0 | D14: =OC!P22 -> 0 | E14: =OC!D22 -> 0 | F14: =OC!E22 -> 0 | G14: =C14*F14 -> 0 | H14: =IF(_xlfn.XLOOKUP(A14,[1]MACHOTE!A:A,[1]MACHOTE!V:V,0,0)="S",1.16,IF(_xlfn.XLOOKUP(A14,[1]MACHOTE!A:A,[1]MACHOTE!Y:Y,0,0)="S",1.08,1)) -> 1 | I14: =E14*C14 -> 0 | J14: =G14-I14 -> 0 | K14: =OC!$B$6 -> 0 | L14: =OC!$B$7 -> 0 | M14: =OC!$B$2 -> 0 | N14: =OC!$B$3 -> 0 | O14: =OC!$B$5 -> 0 | P14: =OC!$B$8 -> 0 | Q14: =OC!$B$4 -> 0 | R14: =OC!J22 -> 0 | S14: 0 | T14: =OC!L22 -> 0 | U14: =OC!M22 -> 0 | V14: =OC!N22 -> 0
A15: =OC!A23 -> 0 | B15: =OC!B23 -> 0 | C15: =OC!C23 -> 0 | D15: =OC!P23 -> 0 | E15: =OC!D23 -> 0 | F15: =OC!E23 -> 0 | G15: =C15*F15 -> 0 | H15: =IF(_xlfn.XLOOKUP(A15,[1]MACHOTE!A:A,[1]MACHOTE!V:V,0,0)="S",1.16,IF(_xlfn.XLOOKUP(A15,[1]MACHOTE!A:A,[1]MACHOTE!Y:Y,0,0)="S",1.08,1)) -> 1 | I15: =E15*C15 -> 0 | J15: =G15-I15 -> 0 | K15: =OC!$B$6 -> 0 | L15: =OC!$B$7 -> 0 | M15: =OC!$B$2 -> 0 | N15: =OC!$B$3 -> 0 | O15: =OC!$B$5 -> 0 | P15: =OC!$B$8 -> 0 | Q15: =OC!$B$4 -> 0 | R15: =OC!J23 -> 0 | S15: 0 | T15: =OC!L23 -> 0 | U15: =OC!M23 -> 0 | V15: =OC!N23 -> 0
A16: =OC!A24 -> 0 | B16: =OC!B24 -> 0 | C16: =OC!C24 -> 0 | D16: =OC!P24 -> 0 | E16: =OC!D24 -> 0 | F16: =OC!E24 -> 0 | G16: =C16*F16 -> 0 | H16: =IF(_xlfn.XLOOKUP(A16,[1]MACHOTE!A:A,[1]MACHOTE!V:V,0,0)="S",1.16,IF(_xlfn.XLOOKUP(A16,[1]MACHOTE!A:A,[1]MACHOTE!Y:Y,0,0)="S",1.08,1)) -> 1 | I16: =E16*C16 -> 0 | J16: =G16-I16 -> 0 | K16: =OC!$B$6 -> 0 | L16: =OC!$B$7 -> 0 | M16: =OC!$B$2 -> 0 | N16: =OC!$B$3 -> 0 | O16: =OC!$B$5 -> 0 | P16: =OC!$B$8 -> 0 | Q16: =OC!$B$4 -> 0 | R16: =OC!J24 -> 0 | S16: 0 | T16: =OC!L24 -> 0 | U16: =OC!M24 -> 0 | V16: =OC!N24 -> 0
... A225: =OC!A233 -> 0 | B225: =OC!B233 -> 0 | C225: =OC!C233 -> 0 | D225: =OC!P233 -> 0 | E225: =OC!D233 -> 0 | F225: =OC!E233 -> 0 | G225: =C225*F225 -> 0 | H225: =IF(_xlfn.XLOOKUP(A225,[1]MACHOTE!A:A,[1]MACHOTE!V:V,0,0)="S",1.16,IF(_xlfn.XLOOKUP(A225,[1]MACHOTE!A:A,[1]MACHOTE!Y:Y,0,0)="S",1.08,1)) -> 1 | I225: =E225*C225 -> 0 | J225: =G225-I225 -> 0 | K225: =OC!$B$6 -> 0 | L225: =OC!$B$7 -> 0 | M225: =OC!$B$2 -> 0 | N225: =OC!$B$3 -> 0 | O225: =OC!$B$5 -> 0 | P225: =OC!$B$8 -> 0 | Q225: =OC!$B$4 -> 0 | R225: =OC!J233 -> 0 | S225: 0 | T225: =OC!L233 -> 0 | U225: =OC!M233 -> 0 | V225: =OC!N233 -> 0

Sheet MACHOTE
A1: CLAVE | B1: CLAVE ALTERNA | C1: DESCRIPCION | D1: SERVICIO (S/N) | E1: INV_MIN | F1: INV_MAX | G1: PRECIO COMPRA | H1: PRECIO 1 | I1: PRECIO 2 | J1: MAYOREO 2 | K1: PRECIO 3 | L1: MAYOREO 3 | M1: PRECIO 4 | N1: MAYOREO 4 | O1: EXIST. | P1: PESO | Q1: CARACTERISTICAS | R1: DEPARTAMENTO | S1: CATEGORIA | T1: RECETA (S/N) | U1: GRANEL (S/N) | V1: IMPUESTO (S/N) | W1: IMP IVA 0(S/N) | X1: IMP IVA(S/N) | Y1: IMP IEPS(S/N)
A2: 780083142506 | C2: loperamida - DILOSTOP - 12 tab - 2 mg - COLLINS | D2: false | E2: 5 | F2: 6 | G2: 8.960 | H2: 16.000000 | I2: 9.700000 | J2: 10.000 | K2: 9.700000 | L2: 15.000 | M2: 9.700000 | N2: 20.000 | O2: 0.0000 | P2: 0.0000 | Q2: LOPERAMIDA | R2: GENERICO | S2: TABLETA | T2: N | U2: N | V2: N | W2: S | X2: N | Y2: N
A3: 7502009740992 | C3: amoxicilina/ácido clavulánico - CLAMOXÍN - 10 tab - 500/125 mg - MAVER | D3: false | E3: 364 | F3: 727 | G3: 43.870 | H3: 62.670000 | I3: 47.856000 | J3: 10.000 | K3: 47.856000 | L3: 15.000 | M3: 47.856000 | N3: 20.000 | O3: 0.0000 | P3: 0.0000 | Q3: AMOXICLAV, CLAVULIN, AUGMENTIN, CLAVIPEN, GIMACLAV,VALCLAN, ACROXIL C, GRAMAXIN | R3: ANTIBIOTICO GENERICO | S3: TABLETA | T3: S | U3: N | V3: N | W3: S | X3: N | Y3: N
A4: 7502004401409 | C4: dexametasona/neomicina/fenilefrina - DEXNE NASAL - sol 1 mg/3.5mg/2.5 mg /1 ml - OFFENBACH - flyer | D4: false | E4: 10 | F4: 20 | G4: 30.250 | H4: 45.000000 | I4: 33.690000 | J4: 10.000 | K4: 33.690000 | L4: 15.000 | M4: 33.690000 | N4: 20.000 | O4: 0.0000 | P4: 0.0000 | Q4: ALIN NASAL | R4: GENERICO | S4: OFTALMICO | T4: N | U4: N | V4: N | W4: S | X4: N | Y4: N
A5: 7502227424407 | C5: ibuprofeno - ALGIDOL - 10 cap - 200 mg - GELpharma | D5: false | E5: 56 | F5: 111 | G5: 10.990 | H5: 16.000000 | I5: 12.000000 | J5: 10.000 | K5: 12.000000 | L5: 15.000 | M5: 12.000000 | N5: 20.000 | O5: 0.0000 | P5: 0.0000 | Q5: ADVIL, EUFENIL, GELUBRIN, ACTRON | R5: GENERICO | S5: GENERICO | T5: N | U5: N | V5: N | W5: S | X5: N | Y5: N
A6: 7501537102845 | C6: diclofenaco - NEDICLON LP - 20 tab - 100 mg - BRULUART | D6: false | E6: 523 | F6: 1046 | G6: 6.630 | H6: 19.000000 | I6: 7.000000 | J6: 10.000 | K6: 7.000000 | L6: 15.000 | M6: 7.000000 | N6: 20.000 | O6: 0.0000 | P6: 0.0000 | Q6: VOLTAREN RETARD, MAFENA RETARD, DICLOEFENACO ULTRA, DOCRIL, VOLFENAC | R6: OTC GENERICO | S6: MEDICAMENTO FRACCION VI | T6: N | U6: N | V6: N | W6: S | X6: N | Y6: N
A7: 7502211784197 | C7: bencidamina - BENIFLANT - 360 ml - sol 0.15 g/100 ml - LOEFFLER | D7: false | E7: 151 | F7: 301 | G7: 38.770 | H7: 67.000000 | I7: 42.750000 | J7: 10.000 | K7: 42.750000 | L7: 15.000 | M7: 42.750000 | N7: 20.000 | O7: 0.0000 | P7: 0.0000 | Q7: VANTAL BUCOFARINGEO, ARTROBEN, BIOBEND | R7: GENERICO | S7: GENERICO | T7: N | U7: N | V7: N | W7: S | X7: N | Y7: N
A8: 785120754858 | C8: atorvastatina - ATORLIP - 10 tab -40 mg - MAVI | D8: false | E8: 34 | F8: 68 | G8: 36.360 | H8: 50.000000 | I8: 39.615000 | J8: 10.000 | K8: 39.615000 | L8: 15.000 | M8: 39.615000 | N8: 20.000 | O8: 0.0000 | P8: 0.0000 | Q8: THOREVA, LIPITOR, BACAT, ODIVITOR, TEINEMIA, ETURION | R8: GENERICO | S8: TABLETA | T8: N | U8: N | V8: N | W8: S | X8: N | Y8: N
A9: 7503003738732 | C9: fluoxetina - ZATIN - 30 cap - 20 mg - WERMAR | D9: false | E9: 42 | F9: 83 | G9: 22.000 | H9: 35.000000 | I9: 25.650000 | J9: 10.000 | K9: 25.650000 | L9: 15.000 | M9: 25.650000 | N9: 20.000 | O9: 0.0000 | P9: 0.0000 | Q9: FARMAXETINA,FLUOXAC, PISAURIT, PROZAC 20, ANIUP, F EXINA, VICSEL, INDOZUL | R9: GENERICO | S9: GENERICO | T9: N | U9: N | V9: N | W9: S | X9: N | Y9: N
A10: 785120754810 | C10: atorvastatina - ATORLIP - 10 tab - 20 mg - MAVI | D10: false | E10: 41 | F10: 82 | G10: 25.670 | H10: 38.000000 | I10: 28.130000 | J10: 10.000 | K10: 28.130000 | L10: 15.000 | M10: 28.130000 | N10: 20.000 | O10: 0.0000 | P10: 0.0000 | Q10: THOREVA, LIPITOR, BACAT, ODIVITOR, TEINEMIA, ETURION | R10: GENERICO | S10: TABLETA | T10: N | U10: N | V10: N | W10: S | X10: N | Y10: N
A11: 7501249600813 | C11: levotiroxina sódica - LEVOTIROXINA - 100 tab - 100 mcg - TEMPUSPHARMA | D11: false | E11: 0 | F11: 0 | G11: 41.010 | H11: 58.000000 | I11: 44.160000 | J11: 10.000 | K11: 44.160000 | L11: 15.000 | M11: 44.160000 | N11: 20.000 | O11: 0.0000 | P11: 0.0000 | Q11: EUTIROX, KARET, LEVOTIROXINA SODICA 100 AMSA | R11: GENERICO | S11: GENERICO | T11: N | U11: N | V11: N | W11: S | X11: N | Y11: N
A12: 7501563310436 | C12: tetraciclina - BIOTRICINA - 10 tab - 250 mg - BIORESEARCH | D12: false | E12: 37 | F12: 74 | G12: 11.490 | H12: 20.000000 | I12: 12.446000 | J12: 10.000 | K12: 12.446000 | L12: 15.000 | M12: 12.446000 | N12: 20.000 | O12: 0.0000 | P12: 0.0000 | Q12: ACROMICINA, | R12: ANTIBIOTICO GENERICO | S12: TABLETA | T12: S | U12: N | V12: N | W12: S | X12: N | Y12: N
A13: 7502254000339 | C13: sertralina - ACORTRAL - 14 tab - 50 mg - ACCORD | D13: false | E13: 130 | F13: 259 | G13: 24.720 | H13: 39.500000 | I13: 28.025000 | J13: 10.000 | K13: 28.025000 | L13: 15.000 | M13: 28.025000 | N13: 20.000 | O13: 0.0000 | P13: 0.0000 | Q13: ALTRULINE, EQUIVAC,RESTERAL, SERENATA, TTRESSVIN, ALUPREX, TRAKOS | R13: GENERICO | S13: TABLETA | T13: N | U13: N | V13: N | W13: S | X13: N | Y13: N
... A23: 7502216792760 | C23: omeprazol - OMEPRAZOL - 30 cap - 20 mg - ULTRA | D23: false | E23: 62 | F23: 124 | G23: 14.970 | H23: 25.000000 | I23: 18.525000 | J23: 10.000 | K23: 18.525000 | L23: 15.000 | M23: 18.525000 | N23: 20.000 | O23: 0.0000 | P23: 0.0000 | Q23: ULTIZOL, CIZOLE, GASTROPAX NF, FABOACID PLUS, TASEC, REFLUPRAZOL, CLANZOL 20, ALBOZ | R23: GENERICO | S23: GENERICO | T23: N | U23: N | V23: N | W23: S | X23: N | Y23: N
A24: 7502216804814 | C24: AMLODIPINO - 100 tab - 5 mg - AVIVIA | D24: false | E24: 37 | F24: 74 | G24: 29.300 | H24: 48.000000 | I24: 31.525000 | J24: 10.000 | K24: 31.525000 | L24: 15.000 | M24: 31.525000 | N24: 20.000 | O24: 0.0000 | P24: 0.0000 | R24: GENERICO | S24: TABLETA | T24: N | U24: N | V24: N | W24: S | X24: N | Y24: N
A25: 7501573908104 | C25: naproxeno - BIXEN - 12 tab - 550 mg - BIOMEP | D25: false | E25: 159 | F25: 317 | G25: 19.360 | H25: 36.000000 | I25: 21.342000 | J25: 10.000 | K25: 21.342000 | L25: 15.000 | M25: 21.342000 | N25: 20.000 | O25: 0.0000 | P25: 0.0000 | Q25: FLANAX, DAFLOXEN, ALLIVIAX, INFLANOX,FLAXENDOL | R25: GENERICO | S25: TABLETA | T25: N | U25: N | V25: N | W25: S | X25: N | Y25: N
A26: 7501573900542 | C26: metronidazol - MESSELDAZOL - 30 tab - 500 mg - BIOMEP | D26: false | E26: 58 | F26: 116 | G26: 14.950 | H26: 27.000000 | I26: 16.320000 | J26: 10.000 | K26: 16.320000 | L26: 15.000 | M26: 16.320000 | N26: 20.000 | O26: 0.0000 | P26: 0.0000 | Q26: FLAGENASE, FLAGYL, LAMBLIT | R26: GENERICO | S26: GENERICO | T26: N | U26: N | V26: N | W26: S | X26: N | Y26: N
A27: 7501573900016 | C27: metronidazol - MESSELDAZOL - 20 tab - 500 mg - BIOMEP | D27: false | E27: 39 | F27: 77 | G27: 12.330 | H27: 20.000000 | I27: 13.110000 | J27: 10.000 | K27: 13.110000 | L27: 15.000 | M27: 13.110000 | N27: 20.000 | O27: 0.0000 | P27: 0.0000 | R27: GENERICO | S27: TABLETA | T27: N | U27: N | V27: N | W27: S | X27: N | Y27: N
A28: 7501573900252 | C28: metformina/glibenclamida - WADIL - 30 tab - 500/5 mg - BIOMEP | D28: false | E28: 12 | F28: 23 | G28: 25.960 | H28: 37.000000 | I28: 28.416000 | J28: 10.000 | K28: 28.416000 | L28: 15.000 | M28: 28.416000 | N28: 20.000 | O28: 0.0000 | P28: 0.0000 | Q28: DIMEFOR G, SIL NORBORAL, GLUCOVANCE, MAVIGLIN | R28: GENERICO | S28: TABLETA | T28: N | U28: N | V28: N | W28: S | X28: N | Y28: N
A29: 7501537102111 | C29: ambroxol - OXOLVAN - 20 tab - 30 mg - BRULUART | D29: false | E29: 108 | F29: 324 | G29: 9.300 | H29: 18.000000 | I29: 10.088000 | J29: 10.000 | K29: 10.088000 | L29: 15.000 | M29: 10.088000 | N29: 20.000 | O29: 0.0000 | P29: 0.0000 | Q29: MUCOVIBROL, MUCOANGIN, CLOXAN, OXOLVAN | R29: GENERICO | S29: GENERICO | T29: N | U29: N | V29: N | W29: S | X29: N | Y29: N
A30: 7501590222214 | C30: ácido fólico - MATERFOL - 90 tab - 400 mcg - CMD | D30: false | E30: 19 | F30: 38 | G30: 18.320 | H30: 29.000000 | I30: 19.872000 | J30: 10.000 | K30: 19.872000 | L30: 15.000 | M30: 19.872000 | N30: 20.000 | O30: 0.0000 | P30: 0.0000 | Q30: A.F. VALDECASAS, FOLIVITAL | R30: GENERICO | S30: TABLETA | T30: N | U30: N | V30: N | W30: S | X30: N | Y30: N
A31: 7501590282829 | C31: vit, min, quercetina y omega 3,6 - DIBENEL MAX - 30 cap - 1.35 g c/u - CMD--- | D31: false | E31: 3 | F31: 5 | G31: 50.830 | H31: 73.276000 | I31: 55.034000 | J31: 10.000 | K31: 55.034000 | L31: 15.000 | M31: 55.034000 | N31: 20.000 | O31: 0.0000 | P31: 0.0000 | R31: GENERICO | S31: GENERICO | T31: N | U31: N | V31: S | W31: N | X31: N | Y31: N
A32: 7501590283956 | C32: Omega 3, 6, 9 - OMG 3 - 60 cap - 1.6 g - CMD | D32: false | E32: 18 | F32: 35 | G32: 86.020 | H32: 113.793000 | I32: 93.517000 | J32: 10.000 | K32: 93.517000 | L32: 15.000 | M32: 93.517000 | N32: 20.000 | O32: 0.0000 | P32: 0.0000 | R32: SUPLEMENTOS Y VITAMINAS | S32: SUPLEMENTOS Y VITAMINAS | T32: N | U32: N | V32: S | W32: N | X32: N | Y32: N
A33: 780083141585 | C33: aciclovir - SOVICLOR - tubo 5 g - 50 mg/1 g - COLLINS | D33: false | E33: 57 | F33: 113 | G33: 17.770 | H33: 25.000000 | I33: 19.200000 | J33: 10.000 | K33: 19.200000 | L33: 15.000 | M33: 19.200000 | N33: 20.000 | O33: 0.0000 | P33: 0.0000 | Q33: CICLOFERON, EUROVIR, CLOVEX, LESACLOR, ZIVERONE | R33: GENERICO | S33: GENERICO | T33: N | U33: N | V33: N | W33: S | X33: N | Y33: N
A34: 780083146818 | C34: Losartán-STAARS*-30 compr-50mg - COLLINS--- | D34: false | E34: 0 | F34: 0 | G34: 0.100 | H34: 35.000000 | I34: 27.900000 | J34: 10.000 | K34: 27.400000 | L34: 15.000 | M34: 0.000000 | N34: 20.000 | O34: 0.0000 | P34: 0.0000 | Q34: LODESTAR, ALDERAN, PUNAB, | R34: DESCONTINUADO | S34: DESCONTINUADO | T34: N | U34: N | V34: N | W34: S | X34: N | Y34: N
A35: 780083141066 | C35: diclofenaco - VOLFENAC - gel 1.235 % - tubo 60 g - COLLINS | D35: false | E35: 66 | F35: 132 | G35: 22.580 | H35: 35.000000 | I35: 24.480000 | J35: 10.000 | K35: 24.480000 | L35: 15.000 | M35: 24.480000 | N35: 20.000 | O35: 0.0000 | P35: 0.0000 | Q35: VOLTAREN, FENAGEL | R35: GENERICO | S35: GENERICO | T35: N | U35: N | V35: N | W35: S | X35: N | Y35: N
A36: 780083141929 | C36: ibuprofeno - DOLPRIN - susp - 2 g/100 ml - COLLINS | D36: false | E36: 220 | F36: 439 | G36: 23.530 | H36: 35.000000 | I36: 25.650000 | J36: 10.000 | K36: 25.650000 | L36: 15.000 | M36: 25.650000 | N36: 20.000 | O36: 0.0000 | P36: 0.0000 | Q36: ACTRON, MOTRIM, TABALON,AFLENO, AFLUSIL, DOLVER | R36: GENERICO | S36: GENERICO | T36: N | U36: N | V36: N | W36: S | X36: N | Y36: N
A37: 7502214983375 | C37: levonorgestrel - LEVONORGESTREL - 1 tab - 1.5 mg - DKT | D37: false | E37: 111 | F37: 221 | G37: 14.490 | H37: 25.000000 | I37: 16.281000 | J37: 10.000 | K37: 16.281000 | L37: 15.000 | M37: 16.281000 | N37: 20.000 | O37: 0.0000 | P37: 0.0000 | R37: GENERICO | S37: TABLETA | T37: N | U37: N | V37: N | W37: S | X37: N | Y37: N
A38: 75049805 | C38: neomicina - NEOMICINA/POLIMIXINA B/GRAMICIDINA - sol oft 15 ml - 1.75 mg - OPKO | D38: false | E38: 57 | F38: 114 | G38: 36.530 | H38: 49.000000 | I38: 39.850000 | J38: 10.000 | K38: 39.850000 | L38: 15.000 | M38: 39.850000 | N38: 20.000 | O38: 0.0000 | P38: 0.0000 | Q38: POLIXIN, SEPTILISIN, SULNED | R38: OFTÁLMICO | S38: OFTÁLMICO | T38: N | U38: N | V38: N | W38: S | X38: N | Y38: N
A39: 7501842952890 | C39: ibuprofeno - ADOPREN - 10 tab - 800 mg - GENETICA | D39: false | E39: 47 | F39: 94 | G39: 18.120 | H39: 29.000000 | I39: 20.900000 | J39: 10.000 | K39: 20.900000 | L39: 15.000 | M39: 20.900000 | N39: 20.000 | O39: 0.0000 | P39: 0.0000 | R39: GENERICO | S39: TABLETA | T39: N | U39: N | V39: N | W39: S | X39: N | Y39: N
A40: 7501842900884 | C40: tramadol - GENCATROL RTD - 10 tab - 100 mg - GENÉTICA | D40: false | E40: 46 | F40: 92 | G40: 40.210 | H40: 54.000000 | I40: 46.550000 | J40: 10.000 | K40: 46.550000 | L40: 15.000 | M40: 46.550000 | N40: 20.000 | O40: 0.0000 | P40: 0.0000 | Q40: TRADOL RETARD, DESIGORT 100 | R40: GENERICO | S40: TABLETA | T40: N | U40: N | V40: N | W40: S | X40: N | Y40: N
A41: 7501842901010 | C41: tramadol - GENCATROL - 10 caps - 50 mg - GENÉTICA | D41: false | E41: 63 | F41: 125 | G41: 17.970 | H41: 35.000000 | I41: 20.425000 | J41: 10.000 | K41: 20.425000 | L41: 15.000 | M41: 20.425000 | N41: 20.000 | O41: 0.0000 | P41: 0.0000 | Q41: TRADOL, ADIOLOL | R41: GENERICO | S41: GENERICO | T41: N | U41: N | V41: N | W41: S | X41: N | Y41: N
A42: 7501385490521 | C42: amoxicillina - AMOXICILINA - 12 cap - 500 mg - HORMONA | D42: false | E42: 130 | F42: 260 | G42: 17.000 | H42: 32.000000 | I42: 23.275000 | J42: 10.000 | K42: 23.275000 | L42: 15.000 | M42: 23.275000 | N42: 20.000 | O42: 0.0000 | P42: 0.0000 | R42: ANTIBIOTICO GENERICO | S42: ANTIBIOTICO | T42: S | U42: N | V42: N | W42: S | X42: N | Y42: N
A43: 7501385490316 | C43: ampicilina - AMPICILINA - 20 cap - 500 mg - HORMONA | D43: false | E43: 291 | F43: 581 | G43: 23.390 | H43: 35.000000 | I43: 25.440000 | J43: 10.000 | K43: 25.440000 | L43: 15.000 | M43: 25.440000 | N43: 20.000 | O43: 0.0000 | P43: 0.0000 | Q43: BINOTAL, BRUPEN,MEXAPIN, PENTREXYL | R43: ANTIBIOTICO GENERICO | S43: ANTIBIOTICO | T43: S | U43: N | V43: N | W43: S | X43: N | Y43: N
A44: 7506022315281 | C44: PRUEBA DE EMBARAZO (MEDITEST) - JAYOR | D44: false | E44: 135 | F44: 270 | G44: 14.180 | H44: 20.259000 | I44: 14.628000 | J44: 10.000 | K44: 14.628000 | L44: 15.000 | M44: 14.628000 | N44: 20.000 | O44: 0.0000 | P44: 0.0000 | R44: PREHOSPITALARIO | S44: PREHOSPITALRIO | T44: N | U44: N | V44: S | W44: N | X44: N | Y44: N
A45: 7502225092486 | C45: levofloxacino - CINA - 7 tab - 750 mg - LANDSTEINER | D45: false | E45: 35 | F45: 70 | G45: 24.710 | H45: 45.000000 | I45: 28.025000 | J45: 10.000 | K45: 28.025000 | L45: 15.000 | M45: 28.025000 | N45: 20.000 | O45: 0.0000 | P45: 0.0000 | Q45: BREDELIN, ELEQUINE, FLUONING, MAXIPLINA, LEFLOXINPROXSAFLO, SIBOFIX, UNIQUIN | R45: ANTIBIOTICO GENERICO | S45: TABLETA | T45: S | U45: N | V45: N | W45: S | X45: N | Y45: N
A46: 7501836000828 | C46: sulfadiazina de plata - ARGENTAL - crema 28 g - 1/100 g - LIFERPAL | D46: false | E46: 25 | F46: 50 | G46: 31.550 | H46: 45.000000 | I46: 34.560000 | J46: 10.000 | K46: 34.560000 | L46: 15.000 | M46: 34.560000 | N46: 20.000 | O46: 0.0000 | P46: 0.0000 | Q46: ARGENTAFIL, ARGEMOL | R46: GENERICO | S46: GENERICO | T46: N | U46: N | V46: N | W46: S | X46: N | Y46: N
A47: 7501836000118 | C47: metocarbamol/paracetamol - CARBAFEN - 30 tab - 400/350 mg - LIFERPAL | D47: false | E47: 7 | F47: 13 | G47: 37.320 | H47: 52.000000 | I47: 40.320000 | J47: 10.000 | K47: 40.320000 | L47: 15.000 | M47: 40.320000 | N47: 20.000 | O47: 0.0000 | P47: 0.0000 | R47: GENERICO | S47: TABLETA | T47: N | U47: N | V47: N | W47: S | X47: N | Y47: N
A48: 7501836000927 | C48: ketoconazol - TINIAZOL SHAMPOO - 120 ml - 2 g/100 ml - LIFERPAL | D48: false | E48: 35 | F48: 70 | G48: 38.190 | H48: 54.000000 | I48: 42.275000 | J48: 10.000 | K48: 42.275000 | L48: 15.000 | M48: 42.275000 | N48: 20.000 | O48: 0.0000 | P48: 0.0000 | Q48: MEDICASP | R48: GENERICO | S48: GENERICO | T48: N | U48: N | V48: N | W48: S | X48: N | Y48: N
A49: 7502211789345 | C49: metformina - METFORMINA - 40 tab - 500 mg - LOEFFLER | D49: false | E49: 58 | F49: 115 | G49: 26.340 | H49: 37.000000 | I49: 28.615000 | J49: 10.000 | K49: 28.615000 | L49: 15.000 | M49: 28.615000 | N49: 20.000 | O49: 0.0000 | P49: 0.0000 | Q49: DABEX XR, DIMEFOR, FICONAX, GLUCOPHAGE, AKSPRI, MEVICFOR, | R49: GENERICO | S49: TABLETA | T49: N | U49: N | V49: N | W49: S | X49: N | Y49: N
A50: 7502211781615 | C50: sulfadiazina - ARGEMOL - crema 1% - 28 g - LOEFFLER | D50: false | E50: 29 | F50: 57 | G50: 29.370 | H50: 42.000000 | I50: 33.250000 | J50: 10.000 | K50: 33.250000 | L50: 15.000 | M50: 33.250000 | N50: 20.000 | O50: 0.0000 | P50: 0.0000 | Q50: ARGENTAFIL, ARGENTAL | R50: GENERICO | S50: GENERICO | T50: N | U50: N | V50: N | W50: S | X50: N | Y50: N
A51: 7502211783954 | C51: nitazoxanida - ROSANIL - 7 tab - 500 mg - LOEFFLER | D51: false | E51: 11 | F51: 21 | G51: 37.690 | H51: 75.000000 | I51: 43.225000 | J51: 10.000 | K51: 43.225000 | L51: 15.000 | M51: 43.225000 | N51: 20.000 | O51: 0.0000 | P51: 0.0000 | Q51: DAXON, PARAMIX, ZOTANIXIN | R51: GENERICO | S51: TABLETA | T51: N | U51: N | V51: N | W51: S | X51: N | Y51: N
A52: 7502211783275 | C52: terbinafina - ERBITRAX - 15 g - crema 1% - LOEFFLER | D52: false | E52: 2 | F52: 4 | G52: 18.710 | H52: 30.000000 | I52: 20.160000 | J52: 10.000 | K52: 20.160000 | L52: 15.000 | M52: 20.160000 | N52: 20.000 | O52: 0.0000 | P52: 0.0000 | Q52: LAMISIL, UNASAL, MYCELVAN, SILKA MEDIC, HUDICLOR, RIXOBA, NAFICH | R52: GENERICO | S52: GENERICO | T52: N | U52: N | V52: N | W52: S | X52: N | Y52: N
A53: 7502009740916 | C53: betametasona - ERISPAN - iny 1 amp - 8 mg/2 ml - MAVER | D53: false | E53: 52 | F53: 104 | G53: 21.400 | H53: 35.000000 | I53: 23.560000 | J53: 10.000 | K53: 23.560000 | L53: 15.000 | M53: 23.560000 | N53: 20.000 | O53: 0.0000 | P53: 0.0000 | Q53: CELESTONE HYPAK , ALIN, CELESBITAN, ROIXOTAN, VERICORT, BRULIN, METAX | R53: GENERICO | S53: INYECCIÓN | T53: N | U53: N | V53: N | W53: S | X53: N | Y53: N
A54: 7502009740480 | C54: cefalexina - CEFALVER - 20 cap - 500 mg - MAVER | D54: false | E54: 137 | F54: 274 | G54: 38.870 | H54: 56.000000 | I54: 42.048000 | J54: 10.000 | K54: 42.048000 | L54: 15.000 | M54: 42.048000 | N54: 20.000 | O54: 0.0000 | P54: 0.0000 | Q54: KEFLEX, NAXIFELAR, FACELIT, OPTOCEF, CEPOREX, C FLIP, NIXELAF C | R54: ANTIBIOTICO GENERICO | S54: ANTIBIOTICO | T54: S | U54: N | V54: N | W54: S | X54: N | Y54: N
A55: 7502009740244 | C55: ketorolaco - LOROTEC - 10 tab -10 mg - MAVER | D55: false | E55: 144 | F55: 287 | G55: 5.370 | H55: 10.000000 | I55: 6.175000 | J55: 10.000 | K55: 6.175000 | L55: 15.000 | M55: 6.175000 | N55: 20.000 | O55: 0.0000 | P55: 0.0000 | Q55: RAPIX, DOLAC, SUPRADOL, ULTILAP, VOYDOL, KENDOL, ONEMER, KETROL, BRUNACOL, MAVIDOL, TOLORAN,DOLIKAN, LANDACO, DOKET, NOVAKEROL | R55: GENERICO | S55: TABLETA | T55: N | U55: N | V55: N | W55: S | X55: N | Y55: N
A56: 7502009747052 | C56: paracetamol - CORIVER 750 - 10 tab - 750 mg - MAVER | D56: false | E56: 64 | F56: 128 | G56: 6.820 | H56: 15.000000 | I56: 7.600000 | J56: 10.000 | K56: 7.600000 | L56: 15.000 | M56: 7.600000 | N56: 20.000 | O56: 0.0000 | P56: 0.0000 | Q56: TYLEX 750, PORTEM, QUITADOL, ACETAFEN, | R56: GENERICO | S56: TABLETA | T56: N | U56: N | V56: N | W56: S | X56: N | Y56: N
A57: 7502009745546 | C57: naproxeno/lidocaína - LUMBOXEN AZUL - gel 35 g - 10/2 g - MAVER | D57: false | E57: 47 | F57: 94 | G57: 34.720 | H57: 55.000000 | I57: 37.440000 | J57: 10.000 | K57: 37.440000 | L57: 15.000 | M57: 37.440000 | N57: 20.000 | O57: 0.0000 | P57: 0.0000 | Q57: ANALGEN NF GEL | R57: GENERICO | S57: GENERICO | T57: N | U57: N | V57: N | W57: S | X57: N | Y57: N
A58: 7502009741289 | C58: cefalexina/bromhexina - CEPOBROM - 12 cap - 500/8.782 mg - MAVER | D58: false | E58: 66 | F58: 132 | G58: 43.090 | H58: 55.000000 | I58: 46.530000 | J58: 10.000 | K58: 46.530000 | L58: 15.000 | M58: 46.530000 | N58: 20.000 | O58: 0.0000 | P58: 0.0000 | Q58: MUCOCEF | R58: ANTIBIOTICO GENERICO | S58: ANTIBIOTICO | T58: S | U58: N | V58: N | W58: S | X58: N | Y58: N
A59: 7502009745836 | C59: mupirocina - BERNIVER - ung 15 g - 2% - MAVER | D59: false | E59: 4 | F59: 6 | G59: 69.050 | H59: 105.000000 | I59: 88.350000 | J59: 10.000 | K59: 88.350000 | L59: 15.000 | M59: 88.350000 | N59: 20.000 | O59: 0.0000 | P59: 0.0000 | Q59: BACTROBAN, SINPEBAC, UNDERAN | R59: ANTIBIOTICO GENERICO | S59: ANTIBIOTICO | T59: S | U59: N | V59: N | W59: S | X59: N | Y59: N
... A61: 7502009745539 | C61: naproxeno/lidocaína - LUMBOXEN ROJO - gel 35 g - 10/2 g - MAVER | D61: false | E61: 29 | F61: 58 | G61: 34.720 | H61: 50.000000 | I61: 38.000000 | J61: 10.000 | K61: 38.000000 | L61: 15.000 | M61: 38.000000 | N61: 20.000 | O61: 0.0000 | P61: 0.0000 | Q61: ANALGEN NF | R61: GENERICO | S61: GENERICO | T61: N | U61: N | V61: N | W61: S | X61: N | Y61: N
A62: 7502009746253 | C62: cefixima - BENEVENTOL - 6 cap - 400 mg - MAVER | D62: false | E62: 52 | F62: 104 | G62: 131.230 | H62: 165.000000 | I62: 141.620000 | J62: 10.000 | K62: 141.620000 | L62: 15.000 | M62: 141.620000 | N62: 20.000 | O62: 0.0000 | P62: 0.0000 | R62: ANTIBIOTICO GENERICO | S62: ANTIBIOTICO | T62: S | U62: N | V62: N | W62: S | X62: N | Y62: N
A63: 7502009744891 | C63: norfenefrina - FRINVER - fco got 24 ml - 10 mg/ml - MAVER | D63: false | E63: 129 | F63: 257 | G63: 56.300 | H63: 72.000000 | I63: 61.920000 | J63: 10.000 | K63: 61.920000 | L63: 15.000 | M63: 61.920000 | N63: 20.000 | O63: 0.0000 | P63: 0.0000 | Q63: A.S. COR | R63: GENERICO | S63: GENERICO | T63: N | U63: N | V63: N | W63: S | X63: N | Y63: N
A64: 7502009740497 | C64: amoxicilina/ácido clavulánico - CLAMOXÍN 12 H PED - susp 40 ml - 200/28.5 mg/5 ml - MAVER | D64: false | E64: 89 | F64: 178 | G64: 22.250 | H64: 32.000000 | I64: 24.225000 | J64: 10.000 | K64: 24.225000 | L64: 15.000 | M64: 24.225000 | N64: 20.000 | O64: 0.0000 | P64: 0.0000 | Q64: CLAVULIN, AUGMENTIN, AMOXICLAV, VALCLAN, GIMACLAV | R64: ANTIBIOTICO GENERICO | S64: ANTIBIOTICO | T64: S | U64: N | V64: N | W64: S | X64: N | Y64: N
A65: 7502009745997 | C65: dexpantenol - PAMEDAN - crema 30 g - 5% - MAVER | D65: false | E65: 25 | F65: 49 | G65: 17.570 | H65: 28.000000 | I65: 19.104000 | J65: 10.000 | K65: 19.104000 | L65: 15.000 | M65: 19.104000 | N65: 20.000 | O65: 0.0000 | P65: 0.0000 | R65: GENERICO | S65: GENERICO | T65: N | U65: N | V65: N | W65: S | X65: N | Y65: N
A66: 7502009745478 | C66: duloxetina - IDELIVER PRO - 14 tab - 60 mg - MAVER | D66: false | E66: 48 | F66: 96 | G66: 53.320 | H66: 70.000000 | I66: 58.900000 | J66: 10.000 | K66: 58.900000 | L66: 15.000 | M66: 58.900000 | N66: 20.000 | O66: 0.0000 | P66: 0.0000 | Q66: CYMBALTA, DULPICAP, KASTANDI, ABRETIA, DHARMA-SEIS, LIMBAXIA, SPLYPAX, ARQUERA | R66: GENERICO | S66: TABLETA | T66: N | U66: N | V66: N | W66: S | X66: N | Y66: N
A67: 7502009747236 | C67: paracetamol/fenilefrina/clorfenamina - EXALIV - 24 tab - 325/5/2 mg - MAVER | D67: false | E67: 75 | F67: 150 | G67: 18.190 | H67: 25.000000 | I67: 19.698000 | J67: 10.000 | K67: 19.698000 | L67: 15.000 | M67: 19.698000 | N67: 20.000 | O67: 0.0000 | P67: 0.0000 | Q67: CONTAC ULTRA, DESENFRIOL D, TEMPRA 24hrs, BREGAMIN, | R67: GENERICO | S67: TABLETA | T67: N | U67: N | V67: N | W67: S | X67: N | Y67: N
A68: 7502009741753 | C68: paracetamol/fenilefrina/dextro - EXALVER - 10 tab - 500/5/15 mg - MAVER | D68: false | E68: 37 | F68: 74 | G68: 11.900 | H68: 20.000000 | I68: 13.132000 | J68: 10.000 | K68: 13.132000 | L68: 15.000 | M68: 13.132000 | N68: 20.000 | O68: 0.0000 | P68: 0.0000 | Q68: XL3 ANTIGRIPAL, DESENFRIOL D, CONTAC ULTRA, | R68: GENERICO | S68: TABLETA | T68: N | U68: N | V68: N | W68: S | X68: N | Y68: N
A69: 7502009745485 | C69: duloxetina - IDELIVER PRO - 7 tab - 30 mg - MAVER | D69: false | E69: 0 | F69: 1 | G69: 27.140 | H69: 50.000000 | I69: 29.925000 | J69: 10.000 | K69: 29.925000 | L69: 15.000 | M69: 29.925000 | N69: 20.000 | O69: 0.0000 | P69: 0.0000 | R69: GENERICO | S69: TABLETA | T69: N | U69: N | V69: N | W69: S | X69: N | Y69: N
A70: 7502009744358 | C70: losartán - ALDERÁN - 15 tab -100 mg - MAVER | D70: false | E70: 39 | F70: 77 | G70: 18.360 | H70: 27.000000 | I70: 20.160000 | J70: 10.000 | K70: 20.160000 | L70: 15.000 | M70: 20.160000 | N70: 20.000 | O70: 0.0000 | P70: 0.0000 | Q70: LODESTAR, COZAAR, | R70: GENERICO | S70: TABLETA | T70: N | U70: N | V70: N | W70: S | X70: N | Y70: N
A71: 7502009745928 | C71: cefixima - BENEVENTOL - 3 cap - 400 mg - MAVER | D71: false | E71: 0 | F71: 0 | G71: 77.970 | H71: 100.000000 | I71: 84.280000 | J71: 10.000 | K71: 84.280000 | L71: 15.000 | M71: 84.280000 | N71: 20.000 | O71: 0.0000 | P71: 0.0000 | Q71: DENVAR, BIOMICS, DEFALOX, ETICEFA, AMIXBRU | R71: ANTIBIOTICO GENERICO | S71: ANTIBIOTICO | T71: S | U71: N | V71: N | W71: S | X71: N | Y71: N
A72: 7502009745584 | C72: lactulosa - OPPELVER - jbe 125 ml - 10 g/15 ml - MAVER | D72: false | E72: 36 | F72: 71 | G72: 44.330 | H72: 62.330000 | I72: 48.093000 | J72: 10.000 | K72: 48.093000 | L72: 15.000 | M72: 48.093000 | N72: 20.000 | O72: 0.0000 | P72: 0.0000 | Q72: LACTULAX, REGULACT, DUPHALAC, QUIMTULAC | R72: GENERICO | S72: JARABE | T72: N | U72: N | V72: N | W72: S | X72: N | Y72: N
A73: 7502009741050 | C73: cefaclor - FASICLOR - susp - 250 mg/75 ml - MAVER | D73: false | E73: 87 | F73: 174 | G73: 74.950 | H73: 99.000000 | I73: 81.340000 | J73: 10.000 | K73: 81.340000 | L73: 15.000 | M73: 81.340000 | N73: 20.000 | O73: 0.0000 | P73: 0.0000 | Q73: CECLOR, CEFLACID | R73: ANTIBIOTICO GENERICO | S73: ANTIBIOTICO | T73: S | U73: N | V73: N | W73: S | X73: N | Y73: N
A74: 785120754681 | C74: hidroxizina - HIDROXIN - 30 tab - 10 mg - MAVI -*FB* | D74: false | E74: 100 | F74: 200 | G74: 30.960 | H74: 45.000000 | I74: 34.105000 | J74: 10.000 | K74: 34.105000 | L74: 15.000 | M74: 34.105000 | N74: 20.000 | O74: 0.0000 | P74: 0.0000 | Q74: ATARAX, AKISKAM, XYLAM | R74: GENERICO | S74: GENERICO | T74: N | U74: N | V74: N | W74: S | X74: N | Y74: N
A75: 785118754235 | C75: bencidamina - ARTROBEN SPRAY - 45 g/30 ml - MAVI | D75: false | E75: 55 | F75: 110 | G75: 26.840 | H75: 38.000000 | I75: 28.992000 | J75: 10.000 | K75: 28.992000 | L75: 15.000 | M75: 28.992000 | N75: 20.000 | O75: 0.0000 | P75: 0.0000 | Q75: VANTAL | R75: GENERICO | S75: GENERICO | T75: N | U75: N | V75: N | W75: S | X75: N | Y75: N
A76: 785118754204 | C76: metformina/glibenclamida - MAVIGLIN - 60 tab - 500/5 mg - MAVI | D76: false | E76: 80 | F76: 159 | G76: 53.880 | H76: 68.000000 | I76: 58.440000 | J76: 10.000 | K76: 58.440000 | L76: 15.000 | M76: 58.440000 | N76: 20.000 | O76: 0.0000 | P76: 0.0000 | Q76: SIL NORBORAL, DIMEFOR G, WADIL | R76: GENERICO | S76: TABLETA | T76: N | U76: N | V76: N | W76: S | X76: N | Y76: N
A77: 785118753962 | C77: sildenafil - FIGRAL - 10 tab -100 mg - MAVI | D77: false | E77: 38 | F77: 76 | G77: 69.810 | H77: 90.000000 | I77: 75.660000 | J77: 10.000 | K77: 75.660000 | L77: 15.000 | M77: 75.660000 | N77: 20.000 | O77: 0.0000 | P77: 0.0000 | Q77: VIAGRA, GO, MAZZOGRAN, VIGOREX, DIONIXOL | R77: GENERICO | S77: TABLETA | T77: N | U77: N | V77: N | W77: S | X77: N | Y77: N
A78: 785118752965 | C78: sildenafil - FIGRAL - 4 tab - 50 mg - MAVI | D78: false | E78: 41 | F78: 82 | G78: 19.910 | H78: 36.900000 | I78: 21.560000 | J78: 10.000 | K78: 21.560000 | L78: 15.000 | M78: 21.560000 | N78: 20.000 | O78: 0.0000 | P78: 0.0000 | Q78: VIAGRA, GO, MAZZOGRAN, VIGOREX, DIONIXOL | R78: GENERICO | S78: TABLETA | T78: N | U78: N | V78: N | W78: S | X78: N | Y78: N
A79: 785118753818 | C79: sildenafil - FIGRAL - caja c/1 tab -100 mg - MAVI | D79: false | E79: 25 | F79: 50 | G79: 16.680 | H79: 27.000000 | I79: 19.095000 | J79: 10.000 | K79: 19.095000 | L79: 15.000 | M79: 19.095000 | N79: 20.000 | O79: 0.0000 | P79: 0.0000 | Q79: VIAGRA, GO, MAZZOGRAN, VIGOREX, DIONIXOL | R79: GENERICO | S79: TABLETA | T79: N | U79: N | V79: N | W79: S | X79: N | Y79: N
A80: 7501075714739 | C80: glibenclamida - REGLUSAN - 50 tab - 5 mg - NOVAG | D80: false | E80: 68 | F80: 135 | G80: 7.590 | H80: 14.430000 | I80: 9.025000 | J80: 10.000 | K80: 9.025000 | L80: 15.000 | M80: 9.025000 | N80: 20.000 | O80: 0.0000 | P80: 0.0000 | R80: GENERICO | S80: TABLETA | T80: N | U80: N | V80: N | W80: S | X80: N | Y80: N
A81: 7501075721164 | C81: telmisartán - NATRAZIM - 28 tab - 80 mg - NOVAG | D81: false | E81: 53 | F81: 105 | G81: 51.650 | H81: 78.000000 | I81: 56.640000 | J81: 10.000 | K81: 56.640000 | L81: 15.000 | M81: 56.640000 | N81: 20.000 | O81: 0.0000 | P81: 0.0000 | Q81: MICARDIS | R81: GENERICO | S81: TABLETA | T81: N | U81: N | V81: N | W81: S | X81: N | Y81: N
A82: 7501075717150 | C82: ketoconazol - LIZOVAG - 10 tab - 200 mg - NOVAG | D82: false | E82: 8 | F82: 16 | G82: 11.090 | H82: 16.000000 | I82: 12.825000 | J82: 10.000 | K82: 12.825000 | L82: 15.000 | M82: 12.825000 | N82: 20.000 | O82: 0.0000 | P82: 0.0000 | Q82: NIZORAL, KETOWEST, MESSELZOL, CONAZOL | R82: GENERICO | S82: TABLETA | T82: N | U82: N | V82: N | W82: S | X82: N | Y82: N
A83: 7501075714135 | C83: metamizol sódico - PIRINOVAG - 10 tab - 500 mg - NOVAG | D83: false | E83: 373 | F83: 745 | G83: 6.590 | H83: 10.000000 | I83: 7.104000 | J83: 10.000 | K83: 7.104000 | L83: 15.000 | M83: 7.104000 | N83: 20.000 | O83: 0.0000 | P83: 0.0000 | Q83: NEO MELUBRINA TABS, MESSELFENIL, METAPIRONA, | R83: GENERICO | S83: TABLETA | T83: N | U83: N | V83: N | W83: S | X83: N | Y83: N
A84: 75006433 | C84: metoclopramida - CIRULAN - fco 20 ml - 400 mg - NOVAG | D84: false | E84: 54 | F84: 107 | G84: 12.310 | H84: 18.000000 | I84: 13.440000 | J84: 10.000 | K84: 13.440000 | L84: 15.000 | M84: 13.440000 | N84: 20.000 | O84: 0.0000 | P84: 0.0000 | Q84: CIRULAN | R84: GENERICO | S84: GENERICO | T84: N | U84: N | V84: N | W84: S | X84: N | Y84: N
A85: 7501075718119 | C85: tamsulosina - AMZUVAG - 20 cap - 0.4 mg - NOVAG --- | D85: false | E85: 0 | F85: 0 | G85: 32.100 | H85: 47.000000 | I85: 35.040000 | J85: 10.000 | K85: 35.040000 | L85: 15.000 | M85: 35.040000 | N85: 20.000 | O85: 0.0000 | P85: 0.0000 | Q85: TAMSULON, UPROSOL, SECOTEX, HIPEBE, FEDROS | R85: DESCONTINUADO | S85: DESCONTINUADO | T85: N | U85: N | V85: N | W85: S | X85: N | Y85: N
A86: 7501075723830 | C86: ambroxol/teofilina - ATROXOLAM - jbe 150 ml - 7-1.5 mg/ml - NOVAG | D86: false | E86: 173 | F86: 345 | G86: 25.470 | H86: 40.000000 | I86: 28.025000 | J86: 10.000 | K86: 28.025000 | L86: 15.000 | M86: 28.025000 | N86: 20.000 | O86: 0.0000 | P86: 0.0000 | Q86: AMINOEFEDRISON NF | R86: GENERICO | S86: JARABE | T86: N | U86: N | V86: N | W86: S | X86: N | Y86: N
A87: 7501075713190 | C87: ketoconazol - LIZOVAG - crema 30 g - 2 g/100 g - NOVAG | D87: false | E87: 49 | F87: 97 | G87: 14.740 | H87: 25.000000 | I87: 17.000000 | J87: 10.000 | K87: 16.500000 | L87: 15.000 | M87: 16.000000 | N87: 20.000 | O87: 0.0000 | P87: 0.0000 | Q87: NIZORAL CREMA | R87: GENERICO | S87: GENERICO | T87: N | U87: N | V87: N | W87: S | X87: N | Y87: N
A88: 7501075713770 | C88: fibra plantago psillyum - NOVAGON NATURAL - pvo - 49.7 g/400 g - NOVAG | D88: false | E88: 14 | F88: 27 | G88: 88.570 | H88: 124.890000 | I88: 101.840000 | J88: 10.000 | K88: 101.840000 | L88: 15.000 | M88: 101.840000 | N88: 20.000 | O88: 0.0000 | P88: 0.0000 | Q88: METAMUCIL, ALEXCIBRAN, MUGASIN | R88: GENERICO | S88: GENERICO | T88: N | U88: N | V88: N | W88: S | X88: N | Y88: N
A89: 7501075713183 | C89: metronidazol - LAMBLIT - susp 120 ml - 5 g - NOVAG | D89: false | E89: 14 | F89: 27 | G89: 17.340 | H89: 30.000000 | I89: 19.950000 | J89: 10.000 | K89: 19.950000 | L89: 15.000 | M89: 19.950000 | N89: 20.000 | O89: 0.0000 | P89: 0.0000 | Q89: FLAGYL SUSP | R89: GENERICO | S89: GENERICO | T89: N | U89: N | V89: N | W89: S | X89: N | Y89: N
A90: 7501075721089 | C90: pregabalina - ANIERNOV - 28 cap - 150 mg - NOVAG | D90: false | E90: 27 | F90: 53 | G90: 56.900 | H90: 102.000000 | I90: 66.500000 | J90: 10.000 | K90: 66.500000 | L90: 15.000 | M90: 66.500000 | N90: 20.000 | O90: 0.0000 | P90: 0.0000 | Q90: LYRICA, PRIKUL, DISMEDOX, BIPALVER | R90: GENERICO | S90: GENERICO | T90: N | U90: N | V90: N | W90: S | X90: N | Y90: N
A91: 7501075718676 | C91: plántago psyllium - NOVAGON (NARANJA/PIÑA) - 400 g - pvo 35 g - NOVAG | D91: false | E91: 12 | F91: 23 | G91: 86.800 | H91: 115.000000 | I91: 96.425000 | J91: 10.000 | K91: 96.425000 | L91: 15.000 | M91: 96.425000 | N91: 20.000 | O91: 0.0000 | P91: 0.0000 | Q91: METAMUCIL, MUGASIN | R91: GENERICO | S91: GENERICO | T91: N | U91: N | V91: N | W91: S | X91: N | Y91: N
A92: 7501075713152 | C92: clortalidona - LORTAL - 20 tab - 50 mg - NOVAG | D92: false | E92: 17 | F92: 33 | G92: 16.210 | H92: 25.000000 | I92: 18.050000 | J92: 10.000 | K92: 18.050000 | L92: 15.000 | M92: 18.050000 | N92: 20.000 | O92: 0.0000 | P92: 0.0000 | Q92: HIGROTON 50 TABS | R92: GENERICO | S92: TABLETA | T92: N | U92: N | V92: N | W92: S | X92: N | Y92: N
... A95: 7501075718546 | C95: bezafibrato - NIBEZVAG - 30 tab - 200 mg - NOVAG | D95: false | E95: 58 | F95: 116 | G95: 22.680 | H95: 35.000000 | I95: 25.650000 | J95: 10.000 | K95: 25.650000 | L95: 15.000 | M95: 25.650000 | N95: 20.000 | O95: 0.0000 | P95: 0.0000 | Q95: FIBROXOL, CEDUR, COLSER, SAPRAME, BRUFIZA, REDALIP, BEZALIP | R95: GENERICO | S95: TABLETA | T95: N | U95: N | V95: N | W95: S | X95: N | Y95: N
A96: 7501130713868 | C96: vitaminas/minerales - GELCAVIT 9m - 30 cap - 1.59 g c/u - PHARMACAPS-PA | D96: false | E96: 13 | F96: 25 | G96: 54.180 | H96: 68.103000 | I96: 58.534000 | J96: 10.000 | K96: 58.534000 | L96: 15.000 | M96: 58.534000 | N96: 20.000 | O96: 0.0000 | P96: 0.0000 | R96: GENERICO | S96: GENERICO | T96: N | U96: N | V96: S | W96: N | X96: N | Y96: N
A97: 7503008344211 | C97: benzonatato - PROGELBEN - 20 cap - 100 mg - PROGELA | D97: false | E97: 255 | F97: 509 | G97: 16.590 | H97: 23.700000 | I97: 18.096000 | J97: 10.000 | K97: 18.096000 | L97: 15.000 | M97: 18.096000 | N97: 20.000 | O97: 0.0000 | P97: 0.0000 | Q97: TESALON, CAPSICOF, PHARBEN, TEXOVEN | R97: GENERICO | S97: GENERICO | T97: N | U97: N | V97: N | W97: S | X97: N | Y97: N
A98: 7503008344914 | C98: ácido ascórbico - RDP - 10 cap - 500 mg - PROGELA | D98: false | E98: 43 | F98: 86 | G98: 21.350 | H98: 35.000000 | I98: 23.560000 | J98: 10.000 | K98: 23.560000 | L98: 15.000 | M98: 23.560000 | N98: 20.000 | O98: 0.0000 | P98: 0.0000 | R98: OTC | S98: OTC | T98: N | U98: N | V98: N | W98: S | X98: N | Y98: N
A99: 7503008344488 | C99: lactobacilos/sup alimenticio - LACTOPRAM - 20 cap - 430 mg - PROGELA | D99: false | E99: 46 | F99: 91 | G99: 20.210 | H99: 29.310000 | I99: 21.539000 | J99: 10.000 | K99: 21.539000 | L99: 15.000 | M99: 21.539000 | N99: 20.000 | O99: 0.0000 | P99: 0.0000 | R99: GENERICO | S99: GENERICO | T99: N | U99: N | V99: S | W99: N | X99: N | Y99: N
A100: 7503008344730 | C100: tamilgentrin - COMPLEJO B - 30 cap - PROGELA | D100: false | E100: 37 | F100: 73 | G100: 38.310 | H100: 55.000000 | I100: 41.325000 | J100: 10.000 | K100: 41.325000 | L100: 15.000 | M100: 41.325000 | N100: 20.000 | O100: 0.0000 | P100: 0.0000 | R100: GENERICO | S100: GENERICO | T100: N | U100: N | V100: N | W100: S | X100: N | Y100: N
A101: 7503008344716 | C101: vitaminas, minerales - LA FEMME - 30 cap - PROGELA | D101: false | E101: 14 | F101: 27 | G101: 72.920 | H101: 106.000000 | I101: 78.850000 | J101: 10.000 | K101: 78.850000 | L101: 15.000 | M101: 78.850000 | N101: 20.000 | O101: 0.0000 | P101: 0.0000 | R101: GENERICO | S101: GENERICO | T101: N | U101: N | V101: N | W101: S | X101: N | Y101: N
A102: 7501384541200 | C102: valproato de magnesio - VALPROATO DE MAGNESIO - 40 tab -200 mg - PSICOFARMA | D102: false | E102: 43 | F102: 85 | G102: 45.080 | H102: 66.000000 | I102: 49.400000 | J102: 10.000 | K102: 49.400000 | L102: 15.000 | M102: 49.400000 | N102: 20.000 | O102: 0.0000 | P102: 0.0000 | Q102: CRIAM, VALPROSID, | R102: GENERICO | S102: TABLETA | T102: N | U102: N | V102: N | W102: S | X102: N | Y102: N
A103: 7501109764761 | C103: oximetazolidina - NAZTRIL - fco 30 ml - sol. 0.05 % - PERRIGO | D103: false | E103: 19 | F103: 37 | G103: 31.840 | H103: 46.000000 | I103: 35.150000 | J103: 10.000 | K103: 35.150000 | L103: 15.000 | M103: 35.150000 | N103: 20.000 | O103: 0.0000 | P103: 0.0000 | Q103: AFRIN, ILIADIN, COLLIFRIN | R103: GENERICO | S103: GENERICO | T103: N | U103: N | V103: N | W103: S | X103: N | Y103: N
A104: 7502227871676 | C104: metoclopramida - CONYSMIN - 20 tab - 10 mg - RAAM | D104: false | E104: 32 | F104: 64 | G104: 7.050 | H104: 10.000000 | I104: 7.584000 | J104: 10.000 | K104: 7.584000 | L104: 15.000 | M104: 7.584000 | N104: 20.000 | O104: 0.0000 | P104: 0.0000 | Q104: CARNOTPRIM, PLASIL, CIRULAN, DIRPASID,MIPRAMID, ITAN | R104: GENERICO | S104: TABLETA | T104: N | U104: N | V104: N | W104: S | X104: N | Y104: N
A105: 7502227874424 | C105: fluconazol - AMEZTRAM - 10 cap - 100 mg - RAAM | D105: false | E105: 0 | F105: 0 | G105: 19.890 | H105: 29.000000 | I105: 21.600000 | J105: 10.000 | K105: 21.600000 | L105: 15.000 | M105: 21.600000 | N105: 20.000 | O105: 0.0000 | P105: 0.0000 | Q105: AFUNGIL, DIFLUCAN, FLUCOXAN, FLERIDUX, FLUKEZOL, FLUZOR, ONGICIL, MARSIN 100, TERPLEX, LANFLUZOL | R105: GENERICO | S105: GENERICO | T105: N | U105: N | V105: N | W105: S | X105: N | Y105: N
A106: 7502227876015 | C106: paracetamol/tramadol - ROMINSOL - 20 tab - 25/37.5 mg - RAAM | D106: false | E106: 153 | F106: 305 | G106: 32.650 | H106: 45.000000 | I106: 35.000000 | J106: 10.000 | K106: 34.500000 | L106: 15.000 | M106: 34.000000 | N106: 20.000 | O106: 0.0000 | P106: 0.0000 | Q106: AUDOR,TAFITRAM, TRAMACET | R106: GENERICO | S106: TABLETA | T106: N | U106: N | V106: N | W106: S | X106: N | Y106: N
A107: 7502227874202 | C107: ketorolaco/tramadol - ORDEGAN - 10 cap - 10/25 mg - RAAM | D107: false | E107: 105 | F107: 209 | G107: 24.400 | H107: 34.860000 | I107: 26.898000 | J107: 10.000 | K107: 26.898000 | L107: 15.000 | M107: 26.898000 | N107: 20.000 | O107: 0.0000 | P107: 0.0000 | Q107: SINERGIX, FORCEDOL, MAVIDOL TR, | R107: GENERICO | S107: GENERICO | T107: N | U107: N | V107: N | W107: S | X107: N | Y107: N
A108: 7502003388107 | C108: dimenhidrinato - VOMISIN - 20 tab - 50 mg - RAYERE | D108: false | E108: 78 | F108: 156 | G108: 33.380 | H108: 46.000000 | I108: 36.000000 | J108: 10.000 | K108: 36.000000 | L108: 15.000 | M108: 36.000000 | N108: 20.000 | O108: 0.0000 | P108: 0.0000 | Q108: DRAMAMINE, DIMICAPS | R108: GENERICO | S108: TABLETA | T108: N | U108: N | V108: N | W108: S | X108: N | Y108: N
A109: 7502003388077 | C109: dimenhidrinato - VOMISIN INF - sol got 15 ml - 25 mg/ml - RAYERE | D109: false | E109: 41 | F109: 82 | G109: 37.990 | H109: 55.000000 | I109: 41.225000 | J109: 10.000 | K109: 41.225000 | L109: 15.000 | M109: 41.225000 | N109: 20.000 | O109: 0.0000 | P109: 0.0000 | Q109: DRAMAMINE | R109: GENERICO | S109: GENERICO | T109: N | U109: N | V109: N | W109: S | X109: N | Y109: N
A110: 7502001165533 | C110: ácido nalidíxico/fenazopiridina - NALIXONE - 20 tab - 500/50 mg - SONS | D110: false | E110: 175 | F110: 349 | G110: 56.710 | H110: 85.000000 | I110: 63.175000 | J110: 10.000 | K110: 63.175000 | L110: 15.000 | M110: 63.175000 | N110: 20.000 | O110: 0.0000 | P110: 0.0000 | Q110: PIRIFUR, AZURON, AZOGEN | R110: ANTIBIOTICO GENERICO | S110: TABLETA | T110: S | U110: N | V110: N | W110: S | X110: N | Y110: N
A111: 7502001165434 | C111: loperamida - LOP - 12 tab - 2 mg - SONS | D111: false | E111: 61 | F111: 122 | G111: 9.630 | H111: 18.000000 | I111: 10.670000 | J111: 10.000 | K111: 10.670000 | L111: 15.000 | M111: 10.670000 | N111: 20.000 | O111: 0.0000 | P111: 0.0000 | Q111: LOMOTIL | R111: GENERICO | S111: TABLETA | T111: N | U111: N | V111: N | W111: S | X111: N | Y111: N
A112: 7502001169289 | C112: trimetropima/sulfametoxazol - BACTROPIN - 14 tab - 160/800 mg - SONS | D112: false | E112: 70 | F112: 140 | G112: 21.400 | H112: 35.000000 | I112: 24.225000 | J112: 10.000 | K112: 24.225000 | L112: 15.000 | M112: 24.225000 | N112: 20.000 | O112: 0.0000 | P112: 0.0000 | Q112: ECTAPRIM F, MAXTRIM F, BACTRIM F, BACTIVER F, SOLTRIM F, BACTELAN, TRIMEXAZOL F | R112: ANTIBIOTICO GENERICO | S112: TABLETA | T112: S | U112: N | V112: N | W112: S | X112: N | Y112: N
...
